straddle/__init__.py
straddle/_base_client.py
straddle/_client.py
straddle/_compat.py
straddle/_constants.py
straddle/_exceptions.py
straddle/_files.py
straddle/_models.py
straddle/_qs.py
straddle/_resource.py
straddle/_response.py
straddle/_streaming.py
straddle/_types.py
straddle/_version.py
straddle/pagination.py
straddle/py.typed
straddle/_utils/__init__.py
straddle/_utils/_compat.py
straddle/_utils/_datetime_parse.py
straddle/_utils/_logs.py
straddle/_utils/_proxy.py
straddle/_utils/_reflection.py
straddle/_utils/_resources_proxy.py
straddle/_utils/_streams.py
straddle/_utils/_sync.py
straddle/_utils/_transform.py
straddle/_utils/_typing.py
straddle/_utils/_utils.py
straddle/lib/.keep
straddle/resources/__init__.py
straddle/resources/charges.py
straddle/resources/funding_events.py
straddle/resources/payments.py
straddle/resources/payouts.py
straddle/resources/reports.py
straddle/resources/bridge/__init__.py
straddle/resources/bridge/bridge.py
straddle/resources/bridge/link.py
straddle/resources/customers/__init__.py
straddle/resources/customers/customers.py
straddle/resources/customers/review.py
straddle/resources/embed/__init__.py
straddle/resources/embed/embed.py
straddle/resources/embed/linked_bank_accounts.py
straddle/resources/embed/organizations.py
straddle/resources/embed/representatives.py
straddle/resources/embed/accounts/__init__.py
straddle/resources/embed/accounts/accounts.py
straddle/resources/embed/accounts/capability_requests.py
straddle/resources/paykeys/__init__.py
straddle/resources/paykeys/paykeys.py
straddle/resources/paykeys/review.py
straddle/types/__init__.py
straddle/types/bridge_initialize_params.py
straddle/types/bridge_token_v1.py
straddle/types/charge_cancel_params.py
straddle/types/charge_create_params.py
straddle/types/charge_hold_params.py
straddle/types/charge_release_params.py
straddle/types/charge_unmask_response.py
straddle/types/charge_update_params.py
straddle/types/charge_v1.py
straddle/types/customer_address_v1.py
straddle-0.3.0.dist-info/METADATA
straddle-0.3.0.dist-info/WHEEL
straddle-0.3.0.dist-info/licenses/LICENSE
straddle-0.3.0.dist-info/RECORD
